{
  "account_value": 3569012.662003,
  "positions": [
    {
      "coin": "BTC",
      "side": "SHORT",
      "size": 191.81387,
      "entry_price": 77753.4,
      "position_value_usd": 11419063.30884,
      "leverage": 8,
      "unrealized_pnl": 3495125.741979,
      "liquidation_price": 70216.7799823037
    },
    {
      "coin": "ETH",
      "side": "SHORT",
      "size": 8471.2124,
      "entry_price": 1757.15,
      "position_value_usd": 13295567.8618,
      "leverage": 10,
      "unrealized_pnl": 1589644.675306,
      "liquidation_price": 1915.0021974009
    }
  ],
  "timestamp_ms": 1782411903023
}