{
  "account_value": 633636.892473,
  "positions": [
    {
      "coin": "BCH",
      "side": "SHORT",
      "size": 20.0,
      "entry_price": 630.0,
      "position_value_usd": 4299.4,
      "leverage": 10,
      "unrealized_pnl": 8300.6,
      "liquidation_price": 118761.7006758095
    },
    {
      "coin": "WLD",
      "side": "SHORT",
      "size": 1090000.0,
      "entry_price": 0.55057,
      "position_value_usd": 402449.8,
      "leverage": 10,
      "unrealized_pnl": 197681.767287,
      "liquidation_price": 2.5443893702
    },
    {
      "coin": "UNI",
      "side": "SHORT",
      "size": 1000.0,
      "entry_price": 8.2836,
      "position_value_usd": 2830.7,
      "leverage": 10,
      "unrealized_pnl": 5452.9,
      "liquidation_price": 2373.7653135162
    },
    {
      "coin": "ZRO",
      "side": "SHORT",
      "size": 3500.0,
      "entry_price": 2.40911,
      "position_value_usd": 2906.89,
      "leverage": 5,
      "unrealized_pnl": 5525.001129,
      "liquidation_price": 647.449070959
    },
    {
      "coin": "NEAR",
      "side": "SHORT",
      "size": 22819.1,
      "entry_price": 2.45554,
      "position_value_usd": 42402.45162,
      "leverage": 10,
      "unrealized_pnl": 13630.769448,
      "liquidation_price": 105.759520101
    },
    {
      "coin": "ORDI",
      "side": "SHORT",
      "size": 1100.0,
      "entry_price": 7.6907,
      "position_value_usd": 3856.82,
      "leverage": 3,
      "unrealized_pnl": 4603.020557,
      "liquidation_price": 1943.3617928766
    },
    {
      "coin": "ZEN",
      "side": "SHORT",
      "size": 1000.0,
      "entry_price": 24.3079,
      "position_value_usd": 4096.9,
      "leverage": 5,
      "unrealized_pnl": 20211.076211,
      "liquidation_price": 2267.2617583564
    },
    {
      "coin": "FIL",
      "side": "SHORT",
      "size": 7000.0,
      "entry_price": 3.24032,
      "position_value_usd": 5222.0,
      "leverage": 5,
      "unrealized_pnl": 17460.257507,
      "liquidation_price": 324.0552654795
    },
    {
      "coin": "kLUNC",
      "side": "SHORT",
      "size": 29000.0,
      "entry_price": 0.043744,
      "position_value_usd": 1768.362,
      "leverage": 3,
      "unrealized_pnl": -499.777254,
      "liquidation_price": 73.641707385
    },
    {
      "coin": "STRK",
      "side": "SHORT",
      "size": 170000.0,
      "entry_price": 0.23365,
      "position_value_usd": 5154.4,
      "leverage": 5,
      "unrealized_pnl": 34566.421073,
      "liquidation_price": 13.3430544609
    },
    {
      "coin": "TNSR",
      "side": "SHORT",
      "size": 90777.7,
      "entry_price": 0.15671,
      "position_value_usd": 3226.239458,
      "leverage": 3,
      "unrealized_pnl": 10999.722538,
      "liquidation_price": 23.5417662226
    },
    {
      "coin": "XLM",
      "side": "SHORT",
      "size": 25000.0,
      "entry_price": 0.22999,
      "position_value_usd": 4997.75,
      "leverage": 5,
      "unrealized_pnl": 752.0,
      "liquidation_price": 90.7265043343
    },
    {
      "coin": "VIRTUAL",
      "side": "SHORT",
      "size": 3000.0,
      "entry_price": 1.443,
      "position_value_usd": 1663.95,
      "leverage": 5,
      "unrealized_pnl": 2665.05,
      "liquidation_price": 754.9429361188
    },
    {
      "coin": "TRUMP",
      "side": "SHORT",
      "size": 2000.0,
      "entry_price": 8.3305,
      "position_value_usd": 3414.0,
      "leverage": 10,
      "unrealized_pnl": 13247.012579,
      "liquidation_price": 1187.1743067581
    },
    {
      "coin": "MELANIA",
      "side": "SHORT",
      "size": 100000.0,
      "entry_price": 0.19318,
      "position_value_usd": 7530.0,
      "leverage": 3,
      "unrealized_pnl": 11788.846145,
      "liquidation_price": 21.4137115216
    },
    {
      "coin": "ANIME",
      "side": "SHORT",
      "size": 502714.0,
      "entry_price": 0.009141,
      "position_value_usd": 1355.819658,
      "leverage": 3,
      "unrealized_pnl": 3239.588849,
      "liquidation_price": 4.2473393855
    },
    {
      "coin": "VVV",
      "side": "SHORT",
      "size": 499.0,
      "entry_price": 9.8186,
      "position_value_usd": 6798.376,
      "leverage": 3,
      "unrealized_pnl": -1898.89225,
      "liquidation_price": 4289.8587738758
    },
    {
      "coin": "BERA",
      "side": "SHORT",
      "size": 17000.0,
      "entry_price": 0.96741,
      "position_value_usd": 3520.02,
      "leverage": 5,
      "unrealized_pnl": 12926.063966,
      "liquidation_price": 133.3344046092
    },
    {
      "coin": "AVNT",
      "side": "SHORT",
      "size": 20000.0,
      "entry_price": 0.41,
      "position_value_usd": 1826.94,
      "leverage": 5,
      "unrealized_pnl": 6373.06,
      "liquidation_price": 113.2495899178
    },
    {
      "coin": "STBL",
      "side": "SHORT",
      "size": 160000.0,
      "entry_price": 0.091833,
      "position_value_usd": 3956.0,
      "leverage": 3,
      "unrealized_pnl": 10737.4,
      "liquidation_price": 13.361232201
    },
    {
      "coin": "0G",
      "side": "SHORT",
      "size": 10000.0,
      "entry_price": 1.141549,
      "position_value_usd": 2071.2,
      "leverage": 3,
      "unrealized_pnl": 9344.299992,
      "liquidation_price": 213.5912352165
    },
    {
      "coin": "ZEC",
      "side": "SHORT",
      "size": 1.0,
      "entry_price": 571.1459,
      "position_value_usd": 422.53,
      "leverage": 10,
      "unrealized_pnl": 148.615944,
      "liquidation_price": 2371357.1435161904
    },
    {
      "coin": "MET",
      "side": "SHORT",
      "size": 50000.0,
      "entry_price": 0.453132,
      "position_value_usd": 9187.5,
      "leverage": 3,
      "unrealized_pnl": 13469.1,
      "liquidation_price": 42.8605730433
    },
    {
      "coin": "ICP",
      "side": "SHORT",
      "size": 1000.0,
      "entry_price": 7.07,
      "position_value_usd": 2188.7,
      "leverage": 5,
      "unrealized_pnl": 4881.3,
      "liquidation_price": 2265.3535583564
    },
    {
      "coin": "FOGO",
      "side": "SHORT",
      "size": 200000.0,
      "entry_price": 0.038816,
      "position_value_usd": 1814.0,
      "leverage": 3,
      "unrealized_pnl": 5949.3,
      "liquidation_price": 10.6782757608
    },
    {
      "coin": "DASH",
      "side": "SHORT",
      "size": 170.0,
      "entry_price": 43.3121,
      "position_value_usd": 5712.85,
      "leverage": 5,
      "unrealized_pnl": 1650.213812,
      "liquidation_price": 13346.3394609198
    },
    {
      "coin": "CHIP",
      "side": "SHORT",
      "size": 70000.0,
      "entry_price": 0.120063,
      "position_value_usd": 2131.01,
      "leverage": 3,
      "unrealized_pnl": 6273.412723,
      "liquidation_price": 30.5138880309
    }
  ],
  "timestamp_ms": 1782945780989
}