{
  "account_value": 787853.948765,
  "positions": [
    {
      "coin": "BTC",
      "side": "SHORT",
      "size": 5.0,
      "entry_price": 75653.9,
      "position_value_usd": 305195.0,
      "leverage": 40,
      "unrealized_pnl": 73074.90549,
      "liquidation_price": 389082.6008782222
    },
    {
      "coin": "ETH",
      "side": "SHORT",
      "size": 100.0,
      "entry_price": 1678.42,
      "position_value_usd": 161780.0,
      "leverage": 25,
      "unrealized_pnl": 6062.54184,
      "liquidation_price": 17899.3757788824
    },
    {
      "coin": "SOL",
      "side": "LONG",
      "size": 1.0,
      "entry_price": 85.713,
      "position_value_usd": 67.829,
      "leverage": 20,
      "unrealized_pnl": -17.884026,
      "liquidation_price": 0.0
    },
    {
      "coin": "AVAX",
      "side": "SHORT",
      "size": 300.0,
      "entry_price": 9.3681,
      "position_value_usd": 1909.35,
      "leverage": 10,
      "unrealized_pnl": 901.093568,
      "liquidation_price": 5278.4937998286
    },
    {
      "coin": "kPEPE",
      "side": "LONG",
      "size": 10000000.0,
      "entry_price": 0.00327,
      "position_value_usd": 25210.0,
      "leverage": 10,
      "unrealized_pnl": -7493.109792,
      "liquidation_price": 0.0
    },
    {
      "coin": "LINK",
      "side": "SHORT",
      "size": 37100.0,
      "entry_price": 8.94254,
      "position_value_usd": 275612.19,
      "leverage": 10,
      "unrealized_pnl": 56156.13069,
      "liquidation_price": 50.060673314
    },
    {
      "coin": "XRP",
      "side": "LONG",
      "size": 335000.0,
      "entry_price": 1.379119,
      "position_value_usd": 359991.0,
      "leverage": 20,
      "unrealized_pnl": -102014.011923,
      "liquidation_price": 0.0
    },
    {
      "coin": "UNI",
      "side": "SHORT",
      "size": 5000.0,
      "entry_price": 3.67535,
      "position_value_usd": 14445.5,
      "leverage": 10,
      "unrealized_pnl": 3931.272068,
      "liquidation_price": 319.2168579897
    },
    {
      "coin": "DOT",
      "side": "LONG",
      "size": 15000.0,
      "entry_price": 1.19484,
      "position_value_usd": 13271.4,
      "leverage": 10,
      "unrealized_pnl": -4651.20658,
      "liquidation_price": 0.0
    },
    {
      "coin": "NEAR",
      "side": "SHORT",
      "size": 1000.0,
      "entry_price": 2.36571,
      "position_value_usd": 1961.2,
      "leverage": 10,
      "unrealized_pnl": 404.51946,
      "liquidation_price": 1583.5999899486
    },
    {
      "coin": "ONDO",
      "side": "SHORT",
      "size": 3000.0,
      "entry_price": 0.442298,
      "position_value_usd": 932.4,
      "leverage": 10,
      "unrealized_pnl": 394.4964,
      "liquidation_price": 527.5237299829
    },
    {
      "coin": "TAO",
      "side": "SHORT",
      "size": 105.0,
      "entry_price": 314.962,
      "position_value_usd": 22879.5,
      "leverage": 5,
      "unrealized_pnl": 10191.57956,
      "liquidation_price": 14596.4344540779
    },
    {
      "coin": "HYPE",
      "side": "SHORT",
      "size": 75500.0,
      "entry_price": 45.1641,
      "position_value_usd": 4748421.5,
      "leverage": 6,
      "unrealized_pnl": -1338527.440868,
      "liquidation_price": 83.841858145
    },
    {
      "coin": "VIRTUAL",
      "side": "SHORT",
      "size": 33000.0,
      "entry_price": 0.67208,
      "position_value_usd": 18169.47,
      "leverage": 5,
      "unrealized_pnl": 4009.289424,
      "liquidation_price": 46.3004723539
    },
    {
      "coin": "PENGU",
      "side": "SHORT",
      "size": 250000.0,
      "entry_price": 0.00891,
      "position_value_usd": 1493.75,
      "leverage": 5,
      "unrealized_pnl": 733.835279,
      "liquidation_price": 6.0449594707
    },
    {
      "coin": "TRUMP",
      "side": "LONG",
      "size": 17000.0,
      "entry_price": 2.97872,
      "position_value_usd": 28704.5,
      "leverage": 10,
      "unrealized_pnl": -21933.80515,
      "liquidation_price": 0.0
    },
    {
      "coin": "VVV",
      "side": "SHORT",
      "size": 200.0,
      "entry_price": 14.6454,
      "position_value_usd": 2569.2,
      "leverage": 3,
      "unrealized_pnl": 359.89501,
      "liquidation_price": 7130.2205547686
    },
    {
      "coin": "XPL",
      "side": "SHORT",
      "size": 2700000.0,
      "entry_price": 0.101597,
      "position_value_usd": 250770.6,
      "leverage": 10,
      "unrealized_pnl": 23543.834293,
      "liquidation_price": 0.6786701444
    },
    {
      "coin": "WLFI",
      "side": "SHORT",
      "size": 750000.0,
      "entry_price": 0.068836,
      "position_value_usd": 42873.0,
      "leverage": 5,
      "unrealized_pnl": 8754.719044,
      "liquidation_price": 2.0701588236
    },
    {
      "coin": "ASTER",
      "side": "SHORT",
      "size": 590000.0,
      "entry_price": 0.734288,
      "position_value_usd": 360242.2,
      "leverage": 5,
      "unrealized_pnl": 72987.887918,
      "liquidation_price": 3.1694717249
    },
    {
      "coin": "ZEC",
      "side": "SHORT",
      "size": 10.0,
      "entry_price": 493.0,
      "position_value_usd": 4158.7,
      "leverage": 10,
      "unrealized_pnl": 771.3,
      "liquidation_price": 158579.7489948571
    },
    {
      "coin": "MON",
      "side": "SHORT",
      "size": 50000.0,
      "entry_price": 0.023885,
      "position_value_usd": 992.85,
      "leverage": 1,
      "unrealized_pnl": 201.414146,
      "liquidation_price": 30.2147793536
    },
    {
      "coin": "LIT",
      "side": "SHORT",
      "size": 12000.0,
      "entry_price": 1.662291,
      "position_value_usd": 19916.4,
      "leverage": 5,
      "unrealized_pnl": 31.1002,
      "liquidation_price": 127.4718764732
    },
    {
      "coin": "XMR",
      "side": "SHORT",
      "size": 155.0,
      "entry_price": 373.898,
      "position_value_usd": 49327.2,
      "leverage": 5,
      "unrealized_pnl": 8627.050488,
      "liquidation_price": 10058.5375334076
    }
  ],
  "timestamp_ms": 1782337803171
}