{
  "account_value": 1251293.325127,
  "positions": [
    {
      "coin": "OP",
      "side": "SHORT",
      "size": 3990559.6,
      "entry_price": 0.23182,
      "position_value_usd": 411745.939528,
      "leverage": 5,
      "unrealized_pnl": 513370.333355,
      "liquidation_price": 1.0878749367
    },
    {
      "coin": "SUI",
      "side": "SHORT",
      "size": 267780.6,
      "entry_price": 0.74665,
      "position_value_usd": 189125.404362,
      "leverage": 10,
      "unrealized_pnl": 10813.373788,
      "liquidation_price": 16.0793108789
    },
    {
      "coin": "kPEPE",
      "side": "SHORT",
      "size": 98328416.0,
      "entry_price": 0.003044,
      "position_value_usd": 240019.663456,
      "leverage": 10,
      "unrealized_pnl": 59314.921856,
      "liquidation_price": 0.0443068439
    },
    {
      "coin": "APT",
      "side": "SHORT",
      "size": 710371.46,
      "entry_price": 1.1221,
      "position_value_usd": 427075.321752,
      "leverage": 10,
      "unrealized_pnl": 370066.379465,
      "liquidation_price": 6.3961992957
    },
    {
      "coin": "DOT",
      "side": "SHORT",
      "size": 607110.6,
      "entry_price": 1.32886,
      "position_value_usd": 513105.594696,
      "leverage": 10,
      "unrealized_pnl": 293660.43,
      "liquidation_price": 7.5037893954
    },
    {
      "coin": "ADA",
      "side": "SHORT",
      "size": 6580923.0,
      "entry_price": 0.235449,
      "position_value_usd": 978978.10548,
      "leverage": 10,
      "unrealized_pnl": 570497.15145,
      "liquidation_price": 0.7742956749
    },
    {
      "coin": "NEAR",
      "side": "LONG",
      "size": 492341.5,
      "entry_price": 1.82836,
      "position_value_usd": 920924.77575,
      "leverage": 10,
      "unrealized_pnl": 20745.93489,
      "liquidation_price": 0.0
    },
    {
      "coin": "STRK",
      "side": "SHORT",
      "size": 10595485.2,
      "entry_price": 0.04206,
      "position_value_usd": 308116.709616,
      "leverage": 5,
      "unrealized_pnl": 137562.107974,
      "liquidation_price": 0.399943982
    },
    {
      "coin": "EIGEN",
      "side": "SHORT",
      "size": 3121652.67,
      "entry_price": 0.3322,
      "position_value_usd": 732651.881649,
      "leverage": 5,
      "unrealized_pnl": 304560.072057,
      "liquidation_price": 1.4934831665
    },
    {
      "coin": "HYPE",
      "side": "SHORT",
      "size": 15411.76,
      "entry_price": 71.3729,
      "position_value_usd": 985366.28736,
      "leverage": 10,
      "unrealized_pnl": 114616.19129,
      "liquidation_price": 331.0438520798
    },
    {
      "coin": "TRUMP",
      "side": "SHORT",
      "size": 563346.0,
      "entry_price": 2.83697,
      "position_value_usd": 957181.1886,
      "leverage": 8,
      "unrealized_pnl": 641019.825963,
      "liquidation_price": 9.006513402
    },
    {
      "coin": "WLFI",
      "side": "SHORT",
      "size": 21126000.0,
      "entry_price": 0.082036,
      "position_value_usd": 1226786.82,
      "leverage": 5,
      "unrealized_pnl": 506311.892037,
      "liquidation_price": 0.2440722642
    },
    {
      "coin": "LIT",
      "side": "LONG",
      "size": 619365.0,
      "entry_price": 1.456383,
      "position_value_usd": 1122103.5705,
      "leverage": 5,
      "unrealized_pnl": 220070.4097,
      "liquidation_price": 0.0
    }
  ],
  "timestamp_ms": 1782571803495
}