{
  "account_value": 1739743.540868,
  "positions": [
    {
      "coin": "OP",
      "side": "SHORT",
      "size": 3990559.6,
      "entry_price": 0.23182,
      "position_value_usd": 429464.024152,
      "leverage": 5,
      "unrealized_pnl": 495652.248731,
      "liquidation_price": 0.9584619075
    },
    {
      "coin": "SUI",
      "side": "SHORT",
      "size": 267780.6,
      "entry_price": 0.74665,
      "position_value_usd": 197115.977466,
      "leverage": 10,
      "unrealized_pnl": 2822.800684,
      "liquidation_price": 14.019439627
    },
    {
      "coin": "kPEPE",
      "side": "SHORT",
      "size": 98328416.0,
      "entry_price": 0.003044,
      "position_value_usd": 282202.55392,
      "leverage": 10,
      "unrealized_pnl": 17132.031392,
      "liquidation_price": 0.0390448732
    },
    {
      "coin": "APT",
      "side": "SHORT",
      "size": 710371.46,
      "entry_price": 1.1221,
      "position_value_usd": 456555.737342,
      "leverage": 10,
      "unrealized_pnl": 340585.963875,
      "liquidation_price": 5.6499647591
    },
    {
      "coin": "DOT",
      "side": "SHORT",
      "size": 607110.6,
      "entry_price": 1.32886,
      "position_value_usd": 590202.56979,
      "leverage": 10,
      "unrealized_pnl": 216563.454906,
      "liquidation_price": 6.745186394
    },
    {
      "coin": "ADA",
      "side": "SHORT",
      "size": 6580923.0,
      "entry_price": 0.235449,
      "position_value_usd": 1082298.59658,
      "leverage": 10,
      "unrealized_pnl": 467176.66035,
      "liquidation_price": 0.7049644213
    },
    {
      "coin": "NEAR",
      "side": "LONG",
      "size": 492341.5,
      "entry_price": 1.82836,
      "position_value_usd": 1116532.0537,
      "leverage": 10,
      "unrealized_pnl": 216353.21284,
      "liquidation_price": 0.0
    },
    {
      "coin": "STRK",
      "side": "SHORT",
      "size": 10595485.2,
      "entry_price": 0.04206,
      "position_value_usd": 360458.406504,
      "leverage": 5,
      "unrealized_pnl": 85220.411086,
      "liquidation_price": 0.3544711429
    },
    {
      "coin": "EIGEN",
      "side": "SHORT",
      "size": 3121652.67,
      "entry_price": 0.3322,
      "position_value_usd": 647118.598491,
      "leverage": 5,
      "unrealized_pnl": 390093.355215,
      "liquidation_price": 1.294972365
    },
    {
      "coin": "HYPE",
      "side": "SHORT",
      "size": 15411.76,
      "entry_price": 71.3729,
      "position_value_usd": 1084880.02168,
      "leverage": 10,
      "unrealized_pnl": 15102.45697,
      "liquidation_price": 301.1919468764
    },
    {
      "coin": "TRUMP",
      "side": "SHORT",
      "size": 563346.0,
      "entry_price": 2.83697,
      "position_value_usd": 1042640.7768,
      "leverage": 8,
      "unrealized_pnl": 555560.237763,
      "liquidation_price": 8.1648911225
    },
    {
      "coin": "WLFI",
      "side": "SHORT",
      "size": 21126000.0,
      "entry_price": 0.082036,
      "position_value_usd": 1267243.11,
      "leverage": 5,
      "unrealized_pnl": 465855.602037,
      "liquidation_price": 0.2207033254
    },
    {
      "coin": "LIT",
      "side": "LONG",
      "size": 619365.0,
      "entry_price": 1.456383,
      "position_value_usd": 995381.4915,
      "leverage": 5,
      "unrealized_pnl": 93348.3307,
      "liquidation_price": 0.0
    }
  ],
  "timestamp_ms": 1781791240096
}