{
  "account_value": 1797107.879364,
  "positions": [
    {
      "coin": "OP",
      "side": "SHORT",
      "size": 3990559.6,
      "entry_price": 0.23182,
      "position_value_usd": 424276.296672,
      "leverage": 5,
      "unrealized_pnl": 500839.976211,
      "liquidation_price": 0.9722770924
    },
    {
      "coin": "SUI",
      "side": "SHORT",
      "size": 267780.6,
      "entry_price": 0.74665,
      "position_value_usd": 192282.537636,
      "leverage": 10,
      "unrealized_pnl": 7656.240514,
      "liquidation_price": 14.2373676403
    },
    {
      "coin": "kPEPE",
      "side": "SHORT",
      "size": 98328416.0,
      "entry_price": 0.003044,
      "position_value_usd": 275614.550048,
      "leverage": 10,
      "unrealized_pnl": 23720.035264,
      "liquidation_price": 0.0396205189
    },
    {
      "coin": "APT",
      "side": "SHORT",
      "size": 710371.46,
      "entry_price": 1.1221,
      "position_value_usd": 447534.0198,
      "leverage": 10,
      "unrealized_pnl": 349607.681417,
      "liquidation_price": 5.7262186903
    },
    {
      "coin": "DOT",
      "side": "SHORT",
      "size": 607110.6,
      "entry_price": 1.32886,
      "position_value_usd": 580488.80019,
      "leverage": 10,
      "unrealized_pnl": 226277.224506,
      "liquidation_price": 6.8292663153
    },
    {
      "coin": "ADA",
      "side": "SHORT",
      "size": 6580923.0,
      "entry_price": 0.235449,
      "position_value_usd": 1064990.76909,
      "leverage": 10,
      "unrealized_pnl": 484484.48784,
      "liquidation_price": 0.7119364686
    },
    {
      "coin": "NEAR",
      "side": "LONG",
      "size": 492341.5,
      "entry_price": 1.82836,
      "position_value_usd": 1072467.48945,
      "leverage": 10,
      "unrealized_pnl": 172288.64859,
      "liquidation_price": 0.0
    },
    {
      "coin": "STRK",
      "side": "SHORT",
      "size": 10595485.2,
      "entry_price": 0.04206,
      "position_value_usd": 358021.444908,
      "leverage": 5,
      "unrealized_pnl": 87657.372682,
      "liquidation_price": 0.3599339493
    },
    {
      "coin": "EIGEN",
      "side": "SHORT",
      "size": 3121652.67,
      "entry_price": 0.3322,
      "position_value_usd": 657732.217569,
      "leverage": 5,
      "unrealized_pnl": 379479.736137,
      "liquidation_price": 1.3176948369
    },
    {
      "coin": "HYPE",
      "side": "SHORT",
      "size": 15411.76,
      "entry_price": 71.3729,
      "position_value_usd": 1047598.97424,
      "leverage": 10,
      "unrealized_pnl": 52383.50441,
      "liquidation_price": 302.8730843033
    },
    {
      "coin": "TRUMP",
      "side": "SHORT",
      "size": 563346.0,
      "entry_price": 2.83697,
      "position_value_usd": 1041626.754,
      "leverage": 8,
      "unrealized_pnl": 556574.260563,
      "liquidation_price": 8.2752607909
    },
    {
      "coin": "WLFI",
      "side": "SHORT",
      "size": 21126000.0,
      "entry_price": 0.082036,
      "position_value_usd": 1243708.746,
      "leverage": 5,
      "unrealized_pnl": 489389.966037,
      "liquidation_price": 0.2224444824
    },
    {
      "coin": "LIT",
      "side": "LONG",
      "size": 619365.0,
      "entry_price": 1.456383,
      "position_value_usd": 990984.0,
      "leverage": 5,
      "unrealized_pnl": 88950.8392,
      "liquidation_price": 0.0
    }
  ],
  "timestamp_ms": 1781807433857
}