{
  "account_value": 62.729447,
  "positions": [
    {
      "coin": "BTC",
      "side": "LONG",
      "size": 0.021,
      "entry_price": 66618.6,
      "position_value_usd": 1307.901,
      "leverage": 20,
      "unrealized_pnl": -91.09,
      "liquidation_price": 0.0
    },
    {
      "coin": "FARTCOIN",
      "side": "LONG",
      "size": 0.1,
      "entry_price": 0.13313,
      "position_value_usd": 0.012329,
      "leverage": 10,
      "unrealized_pnl": -0.000984,
      "liquidation_price": 0.0
    }
  ],
  "timestamp_ms": 1782221702199
}