{
  "account_value": 2092962.982012,
  "positions": [
    {
      "coin": "LDO",
      "side": "LONG",
      "size": 1759490.8,
      "entry_price": 0.99916,
      "position_value_usd": 488135.532644,
      "leverage": 1,
      "unrealized_pnl": -1269887.230182,
      "liquidation_price": 0.0
    },
    {
      "coin": "ONDO",
      "side": "LONG",
      "size": 1745500.0,
      "entry_price": 0.992029,
      "position_value_usd": 586488.0,
      "leverage": 1,
      "unrealized_pnl": -1145100.240749,
      "liquidation_price": 0.0
    },
    {
      "coin": "ENA",
      "side": "LONG",
      "size": 5431981.0,
      "entry_price": 0.57887,
      "position_value_usd": 523143.226148,
      "leverage": 1,
      "unrealized_pnl": -2621269.955352,
      "liquidation_price": 0.0
    },
    {
      "coin": "WLFI",
      "side": "LONG",
      "size": 5929745.0,
      "entry_price": 0.195226,
      "position_value_usd": 350477.578225,
      "leverage": 1,
      "unrealized_pnl": -807168.534535,
      "liquidation_price": 0.0
    },
    {
      "coin": "STBL",
      "side": "LONG",
      "size": 1915072.0,
      "entry_price": 0.165307,
      "position_value_usd": 49625.260736,
      "leverage": 1,
      "unrealized_pnl": -266949.909054,
      "liquidation_price": 0.0
    }
  ],
  "timestamp_ms": 1782141002600
}