{
  "account_value": 2047002.97355,
  "positions": [
    {
      "coin": "LDO",
      "side": "LONG",
      "size": 1759490.8,
      "entry_price": 0.99916,
      "position_value_usd": 483736.805644,
      "leverage": 1,
      "unrealized_pnl": -1274285.957182,
      "liquidation_price": 0.0
    },
    {
      "coin": "ONDO",
      "side": "LONG",
      "size": 1745500.0,
      "entry_price": 0.992029,
      "position_value_usd": 587832.035,
      "leverage": 1,
      "unrealized_pnl": -1143756.205749,
      "liquidation_price": 0.0
    },
    {
      "coin": "ENA",
      "side": "LONG",
      "size": 5431981.0,
      "entry_price": 0.57887,
      "position_value_usd": 486026.499975,
      "leverage": 1,
      "unrealized_pnl": -2658386.681525,
      "liquidation_price": 0.0
    },
    {
      "coin": "WLFI",
      "side": "LONG",
      "size": 5929745.0,
      "entry_price": 0.195226,
      "position_value_usd": 346172.583355,
      "leverage": 1,
      "unrealized_pnl": -811473.529405,
      "liquidation_price": 0.0
    },
    {
      "coin": "STBL",
      "side": "LONG",
      "size": 1915072.0,
      "entry_price": 0.165307,
      "position_value_usd": 47568.473408,
      "leverage": 1,
      "unrealized_pnl": -269006.696382,
      "liquidation_price": 0.0
    }
  ],
  "timestamp_ms": 1782022524749
}