{
  "account_value": 5870188.461721,
  "positions": [
    {
      "coin": "BTC",
      "side": "SHORT",
      "size": 100.0,
      "entry_price": 72401.0,
      "position_value_usd": 6407500.0,
      "leverage": 20,
      "unrealized_pnl": 832607.815336,
      "liquidation_price": 189463.9340419358
    },
    {
      "coin": "ETH",
      "side": "SHORT",
      "size": 3000.0,
      "entry_price": 2314.09,
      "position_value_usd": 5214000.0,
      "leverage": 20,
      "unrealized_pnl": 1728278.61679,
      "liquidation_price": 5886.8985528582
    },
    {
      "coin": "HYPE",
      "side": "LONG",
      "size": 493500.0,
      "entry_price": 39.6337,
      "position_value_usd": 34978786.5,
      "leverage": 10,
      "unrealized_pnl": 15419552.71172,
      "liquidation_price": 42.294896495
    }
  ],
  "timestamp_ms": 1781970919424
}