{
  "account_value": 601691.839971,
  "positions": [
    {
      "coin": "BTC",
      "side": "LONG",
      "size": 0.03112,
      "entry_price": 73618.9,
      "position_value_usd": 1863.83904,
      "leverage": 20,
      "unrealized_pnl": -427.183211,
      "liquidation_price": 0.0
    },
    {
      "coin": "SOL",
      "side": "SHORT",
      "size": 538.81,
      "entry_price": 83.8648,
      "position_value_usd": 37925.75828,
      "leverage": 20,
      "unrealized_pnl": 7261.46502,
      "liquidation_price": 8066.5359228743
    },
    {
      "coin": "HYPE",
      "side": "SHORT",
      "size": 6521.65,
      "entry_price": 38.9851,
      "position_value_usd": 402972.7535,
      "leverage": 10,
      "unrealized_pnl": -148725.51952,
      "liquidation_price": 706.6917355573
    },
    {
      "coin": "FARTCOIN",
      "side": "SHORT",
      "size": 0.1,
      "entry_price": 0.16342,
      "position_value_usd": 0.012743,
      "leverage": 10,
      "unrealized_pnl": 0.003599,
      "liquidation_price": 42058234.1644
    },
    {
      "coin": "WLFI",
      "side": "SHORT",
      "size": 12643319.0,
      "entry_price": 0.226638,
      "position_value_usd": 732541.259541,
      "leverage": 5,
      "unrealized_pnl": 2132916.517064,
      "liquidation_price": 0.3754703075
    },
    {
      "coin": "ASTER",
      "side": "SHORT",
      "size": 769990.0,
      "entry_price": 1.39211,
      "position_value_usd": 477670.9964,
      "leverage": 3,
      "unrealized_pnl": 594240.15647,
      "liquidation_price": 5.8342583787
    },
    {
      "coin": "MEGA",
      "side": "SHORT",
      "size": 10768092.0,
      "entry_price": 0.133232,
      "position_value_usd": 516060.8091,
      "leverage": 3,
      "unrealized_pnl": 918599.647163,
      "liquidation_price": 0.3994488413
    },
    {
      "coin": "CHIP",
      "side": "SHORT",
      "size": 8183208.0,
      "entry_price": 0.063346,
      "position_value_usd": 252934.776072,
      "leverage": 3,
      "unrealized_pnl": 265441.909272,
      "liquidation_price": 0.4934710005
    }
  ],
  "timestamp_ms": 1782625501791
}