{
  "account_value": 620553.891736,
  "positions": [
    {
      "coin": "BTC",
      "side": "LONG",
      "size": 0.03112,
      "entry_price": 73618.9,
      "position_value_usd": 1860.5092,
      "leverage": 20,
      "unrealized_pnl": -430.513051,
      "liquidation_price": 0.0
    },
    {
      "coin": "SOL",
      "side": "SHORT",
      "size": 538.81,
      "entry_price": 83.8648,
      "position_value_usd": 36711.81935,
      "leverage": 20,
      "unrealized_pnl": 8475.40395,
      "liquidation_price": 8106.1347716743
    },
    {
      "coin": "HYPE",
      "side": "SHORT",
      "size": 6521.65,
      "entry_price": 38.9851,
      "position_value_usd": 413557.39145,
      "leverage": 10,
      "unrealized_pnl": -159310.15747,
      "liquidation_price": 711.6901520939
    },
    {
      "coin": "FARTCOIN",
      "side": "SHORT",
      "size": 0.1,
      "entry_price": 0.16342,
      "position_value_usd": 0.011888,
      "leverage": 10,
      "unrealized_pnl": 0.004454,
      "liquidation_price": 42278367.00840952
    },
    {
      "coin": "WLFI",
      "side": "SHORT",
      "size": 12643319.0,
      "entry_price": 0.226638,
      "position_value_usd": 728798.837117,
      "leverage": 5,
      "unrealized_pnl": 2136658.939488,
      "liquidation_price": 0.3768362667
    },
    {
      "coin": "ASTER",
      "side": "SHORT",
      "size": 769990.0,
      "entry_price": 1.39211,
      "position_value_usd": 481035.8527,
      "leverage": 3,
      "unrealized_pnl": 590875.30017,
      "liquidation_price": 5.8659179297
    },
    {
      "coin": "MEGA",
      "side": "SHORT",
      "size": 10768092.0,
      "entry_price": 0.133232,
      "position_value_usd": 500393.23524,
      "leverage": 3,
      "unrealized_pnl": 934267.221023,
      "liquidation_price": 0.3998337176
    },
    {
      "coin": "CHIP",
      "side": "SHORT",
      "size": 8183208.0,
      "entry_price": 0.063346,
      "position_value_usd": 240324.452544,
      "leverage": 3,
      "unrealized_pnl": 278052.2328,
      "liquidation_price": 0.4943510507
    }
  ],
  "timestamp_ms": 1782446102499
}