{
  "account_value": 623578.591942,
  "positions": [
    {
      "coin": "BTC",
      "side": "LONG",
      "size": 0.03112,
      "entry_price": 73618.9,
      "position_value_usd": 1879.43016,
      "leverage": 20,
      "unrealized_pnl": -411.592091,
      "liquidation_price": 0.0
    },
    {
      "coin": "SOL",
      "side": "SHORT",
      "size": 538.81,
      "entry_price": 83.8648,
      "position_value_usd": 38910.16415,
      "leverage": 20,
      "unrealized_pnl": 6277.05915,
      "liquidation_price": 8117.5465391674
    },
    {
      "coin": "HYPE",
      "side": "SHORT",
      "size": 6521.65,
      "entry_price": 38.9851,
      "position_value_usd": 413322.61205,
      "leverage": 10,
      "unrealized_pnl": -159075.37807,
      "liquidation_price": 712.245470517
    },
    {
      "coin": "FARTCOIN",
      "side": "SHORT",
      "size": 0.1,
      "entry_price": 0.16342,
      "position_value_usd": 0.013083,
      "leverage": 10,
      "unrealized_pnl": 0.003259,
      "liquidation_price": 42316930.73830476
    },
    {
      "coin": "WLFI",
      "side": "SHORT",
      "size": 12643319.0,
      "entry_price": 0.226638,
      "position_value_usd": 730644.761691,
      "leverage": 5,
      "unrealized_pnl": 2134813.014914,
      "liquidation_price": 0.3772734151
    },
    {
      "coin": "ASTER",
      "side": "SHORT",
      "size": 769990.0,
      "entry_price": 1.39211,
      "position_value_usd": 483869.4159,
      "leverage": 3,
      "unrealized_pnl": 588041.73697,
      "liquidation_price": 5.874378618
    },
    {
      "coin": "MEGA",
      "side": "SHORT",
      "size": 10768092.0,
      "entry_price": 0.133232,
      "position_value_usd": 490605.039612,
      "leverage": 3,
      "unrealized_pnl": 944055.416651,
      "liquidation_price": 0.3992470341
    },
    {
      "coin": "CHIP",
      "side": "SHORT",
      "size": 8183208.0,
      "entry_price": 0.063346,
      "position_value_usd": 240897.277104,
      "leverage": 3,
      "unrealized_pnl": 277479.40824,
      "liquidation_price": 0.4948451795
    }
  ],
  "timestamp_ms": 1782565803206
}