{
  "account_value": 627975.680155,
  "positions": [
    {
      "coin": "BTC",
      "side": "LONG",
      "size": 0.03112,
      "entry_price": 73618.9,
      "position_value_usd": 1847.1276,
      "leverage": 20,
      "unrealized_pnl": -443.894651,
      "liquidation_price": 0.0
    },
    {
      "coin": "SOL",
      "side": "SHORT",
      "size": 538.81,
      "entry_price": 83.8648,
      "position_value_usd": 35521.58806,
      "leverage": 20,
      "unrealized_pnl": 9665.63524,
      "liquidation_price": 8120.3791064971
    },
    {
      "coin": "HYPE",
      "side": "SHORT",
      "size": 6521.65,
      "entry_price": 38.9851,
      "position_value_usd": 412487.84085,
      "leverage": 10,
      "unrealized_pnl": -158240.60687,
      "liquidation_price": 712.8531390737
    },
    {
      "coin": "FARTCOIN",
      "side": "SHORT",
      "size": 0.1,
      "entry_price": 0.16342,
      "position_value_usd": 0.011473,
      "leverage": 10,
      "unrealized_pnl": 0.004869,
      "liquidation_price": 42364908.450628564
    },
    {
      "coin": "WLFI",
      "side": "SHORT",
      "size": 12643319.0,
      "entry_price": 0.226638,
      "position_value_usd": 746385.693846,
      "leverage": 5,
      "unrealized_pnl": 2119072.082759,
      "liquidation_price": 0.3788806375
    },
    {
      "coin": "ASTER",
      "side": "SHORT",
      "size": 769990.0,
      "entry_price": 1.39211,
      "position_value_usd": 474221.4412,
      "leverage": 3,
      "unrealized_pnl": 597689.71167,
      "liquidation_price": 5.8677963475
    },
    {
      "coin": "MEGA",
      "side": "SHORT",
      "size": 10768092.0,
      "entry_price": 0.133232,
      "position_value_usd": 492909.4113,
      "leverage": 3,
      "unrealized_pnl": 941751.044963,
      "liquidation_price": 0.3998620333
    },
    {
      "coin": "CHIP",
      "side": "SHORT",
      "size": 8183208.0,
      "entry_price": 0.063346,
      "position_value_usd": 231854.832264,
      "leverage": 3,
      "unrealized_pnl": 286521.85308,
      "liquidation_price": 0.4942678449
    }
  ],
  "timestamp_ms": 1782414302793
}