{
  "account_value": 622101.85782,
  "positions": [
    {
      "coin": "BTC",
      "side": "LONG",
      "size": 0.03112,
      "entry_price": 73618.9,
      "position_value_usd": 1877.25176,
      "leverage": 20,
      "unrealized_pnl": -413.770491,
      "liquidation_price": 0.0
    },
    {
      "coin": "SOL",
      "side": "SHORT",
      "size": 538.81,
      "entry_price": 83.8648,
      "position_value_usd": 38670.3937,
      "leverage": 20,
      "unrealized_pnl": 6516.8296,
      "liquidation_price": 8114.4360816633
    },
    {
      "coin": "HYPE",
      "side": "SHORT",
      "size": 6521.65,
      "entry_price": 38.9851,
      "position_value_usd": 413818.25745,
      "leverage": 10,
      "unrealized_pnl": -159571.02347,
      "liquidation_price": 712.1064972339
    },
    {
      "coin": "FARTCOIN",
      "side": "SHORT",
      "size": 0.1,
      "entry_price": 0.16342,
      "position_value_usd": 0.012918,
      "leverage": 10,
      "unrealized_pnl": 0.003424,
      "liquidation_price": 42302910.93153333
    },
    {
      "coin": "WLFI",
      "side": "SHORT",
      "size": 12643319.0,
      "entry_price": 0.226638,
      "position_value_usd": 733312.502,
      "leverage": 5,
      "unrealized_pnl": 2132145.274605,
      "liquidation_price": 0.3773785684
    },
    {
      "coin": "ASTER",
      "side": "SHORT",
      "size": 769990.0,
      "entry_price": 1.39211,
      "position_value_usd": 484608.6063,
      "leverage": 3,
      "unrealized_pnl": 587302.54657,
      "liquidation_price": 5.8736006031
    },
    {
      "coin": "MEGA",
      "side": "SHORT",
      "size": 10768092.0,
      "entry_price": 0.133232,
      "position_value_usd": 488117.61036,
      "leverage": 3,
      "unrealized_pnl": 946542.845903,
      "liquidation_price": 0.3988988562
    },
    {
      "coin": "CHIP",
      "side": "SHORT",
      "size": 8183208.0,
      "entry_price": 0.063346,
      "position_value_usd": 241200.0558,
      "leverage": 3,
      "unrealized_pnl": 277176.629544,
      "liquidation_price": 0.4947279879
    }
  ],
  "timestamp_ms": 1782561303693
}